bettered.py
bettered-1.1.0.dist-info/entry_points.txt
bettered-1.1.0.dist-info/LICENSE
bettered-1.1.0.dist-info/WHEEL
bettered-1.1.0.dist-info/METADATA
bettered-1.1.0.dist-info/RECORD
