Metadata-Version: 2.1
Name: bettered
Version: 1.1.0
Summary: Automatic helper for redacted better.php.
Home-page: https://github.com/jtpavlock/bettered
License: MIT
Author: Jacob Pavlock
Author-email: jtpavlock@gmail.com
Requires-Python: >=3.9,<3.12
Classifier: Development Status :: 5 - Production/Stable
Classifier: License :: OSI Approved :: MIT License
Classifier: Programming Language :: Python :: 3
Classifier: Programming Language :: Python :: 3.9
Classifier: Programming Language :: Python :: 3.10
Classifier: Programming Language :: Python :: 3.11
Requires-Dist: moe-transcode (>=1.1.0,<2.0.0)
Project-URL: Repository, https://github.com/jtpavlock/bettered
